my_ai_lib/__init__.py
my_ai_lib/core.py
my_ai_lib_lena-0.1.0.dist-info/METADATA
my_ai_lib_lena-0.1.0.dist-info/WHEEL
my_ai_lib_lena-0.1.0.dist-info/top_level.txt
my_ai_lib_lena-0.1.0.dist-info/RECORD
