Metadata-Version: 2.4
Name: my-ai-lib-lena
Version: 0.1.0
Summary: A simple AI helper library for generating responses
Author: Lena Mathew
Requires-Dist: requests
Dynamic: author
Dynamic: requires-dist
Dynamic: summary
